suitable_class_finder/__init__.py
suitable_class_finder/suitable_class_finder.py
suitable_class_finder-0.1.0.dist-info/LICENSE
suitable_class_finder-0.1.0.dist-info/METADATA
suitable_class_finder-0.1.0.dist-info/WHEEL
suitable_class_finder-0.1.0.dist-info/RECORD
