Metadata-Version: 2.1
Name: suitable-class-finder
Version: 0.1.0
Summary: Given the hierarchy of an abstract class, it detects the appropriate concrete subclass (deterministically) that satisfies certain attributes obtained as a parameter. Useful for implementing the Strategy design pattern.
Home-page: https://github.com/EzequielPuerta/suitable-class-finder
License: MIT
Author: Armando Ezequiel Puerta
Author-email: armando.ezequiel.puerta@gmail.com
Requires-Python: >=3.10,<4.0
Classifier: Development Status :: 5 - Production/Stable
Classifier: Intended Audience :: Developers
Classifier: License :: OSI Approved :: MIT License
Classifier: Operating System :: OS Independent
Classifier: Programming Language :: Python :: 3
Classifier: Programming Language :: Python :: 3.10
Classifier: Programming Language :: Python :: 3.11
Classifier: Programming Language :: Python :: 3.12
Classifier: Topic :: Software Development
Project-URL: Bug Tracker, https://github.com/EzequielPuerta/suitable-class-finder/issues
Project-URL: Documentation, https://github.com/EzequielPuerta/suitable-class-finder
Project-URL: Repository, https://github.com/EzequielPuerta/suitable-class-finder
